[
  {
    "id": 2,
    "name": "T-shirt",
    "price": 19.99,
    "image": "/men_tshirt_1.jpg",
    "category": "fashion"
  },
  {
    "id": 3,
    "name": "Smartphone",
    "price": 599.99,
    "image": "/iphone13.jpg",
    "category": "electronics"
  },
  {
    "id": 4,
    "name": "T-shirt",
    "price": 19.99,
    "image": "/men_tshirt_1.jpg",
    "category": "fashion"
  },
  {
    "id": 5,
    "name": "microsoft surface 2",
    "price": 999,
    "image": "/uploads/1728724116320.jfif",
    "category": "electronics"
  },
  {
    "id": 6,
    "name": "poco f6",
    "price": 320,
    "category": "electronics",
    "image": "/uploads/1728724504654.jpg",
    "owner": "aliahanch28"
  },
  {
    "id": 8,
    "name": "Apple iPhone 16 256 6",
    "price": 1300,
    "category": "electronics",
    "image": "/uploads/1728798067941.jpg",
    "owner": "aliahanch28"
  }
]